benekli/__init__.py
benekli/__main__.py
benekli/benekli.py
benekli/constants.py
benekli/formulas.py
benekli-2025.1.dist-info/licenses/LICENSE
benekli-2025.1.dist-info/METADATA
benekli-2025.1.dist-info/WHEEL
benekli-2025.1.dist-info/entry_points.txt
benekli-2025.1.dist-info/top_level.txt
benekli-2025.1.dist-info/RECORD
