Metadata-Version: 2.4
Name: benekli
Version: 2025.1
Summary: tool to investigate the effect of color profile
Author-email: Mete Balci <metebalci@gmail.com>
Project-URL: Homepage, https://github.com/metebalci/benekli
Project-URL: Documentation, https://github.com/metebalci/benekli
Project-URL: Repository, https://github.com/metebalci/benekli.git
Project-URL: Issues, https://github.com/metebalci/benekli/issues
Project-URL: Changelog, https://github.com/metebalci/benekli/blob/master/README.md
Keywords: color management
Classifier: Development Status :: 3 - Alpha
Classifier: Environment :: Console
Classifier: License :: OSI Approved :: GNU General Public License v3 or later (GPLv3+)
Classifier: Programming Language :: Python :: 3.12
Classifier: Topic :: Utilities
Requires-Python: >=3.12
License-File: LICENSE
Requires-Dist: pillow
Provides-Extra: dev
Requires-Dist: setuptools>=61.0; extra == "dev"
Requires-Dist: black; extra == "dev"
Requires-Dist: pylint; extra == "dev"
Requires-Dist: mypy; extra == "dev"
Requires-Dist: build; extra == "dev"
Requires-Dist: twine; extra == "dev"
Requires-Dist: reuse; extra == "dev"
Dynamic: license-file
